magic.py
file_magic-0.4.1.dist-info/LICENSE
file_magic-0.4.1.dist-info/METADATA
file_magic-0.4.1.dist-info/WHEEL
file_magic-0.4.1.dist-info/entry_points.txt
file_magic-0.4.1.dist-info/top_level.txt
file_magic-0.4.1.dist-info/RECORD
