Metadata-Version: 2.1
Name: file-magic
Version: 0.4.1
Summary: Python front end for libmagic(3)
Home-page: https://github.com/file/file
Author: Reuben Thomas, Álvaro Justen
Author-email: Christos Zoulas <christos@astron.com>
License: Copyright (c) Ian F. Darwin 1986-1995.
Project-URL: Homepage, https://https://darwinsys.com/file/
Keywords: file,magic
Classifier: License :: OSI Approved :: BSD License
Classifier: Programming Language :: Python
Classifier: Programming Language :: Python :: 3
Requires-Python: >=2.7
License-File: LICENSE
Provides-Extra: dev
